hfmonthlyreportALL/__init__.py
hfmonthlyreportALL-0.7.dist-info/METADATA
hfmonthlyreportALL-0.7.dist-info/WHEEL
hfmonthlyreportALL-0.7.dist-info/top_level.txt
hfmonthlyreportALL-0.7.dist-info/RECORD
